tfunicode-2.2.0.data/purelib/tfunicode/__init__.py
tfunicode-2.2.0.data/purelib/tfunicode/python/__init__.py
tfunicode-2.2.0.data/purelib/tfunicode/python/ops/__init__.py
tfunicode-2.2.0.data/purelib/tfunicode/python/ops/_tfunicode_ops.so
tfunicode-2.2.0.dist-info/METADATA
tfunicode-2.2.0.dist-info/RECORD
tfunicode-2.2.0.dist-info/WHEEL
tfunicode-2.2.0.dist-info/top_level.txt
