Metadata-Version: 2.1
Name: tfunicode
Version: 2.2.0
Summary: Unicode string ops for TensorFlow
Home-page: https://github.com/shkarupa-alex/tfunicode
Author: Shkarupa Alex
Author-email: shkarupa.alex@gmail.com
License: MIT
Keywords: tensorflow unicode string op
Platform: UNKNOWN
Classifier: Development Status :: 5 - Production/Stable
Classifier: Intended Audience :: Developers
Classifier: Intended Audience :: Education
Classifier: Intended Audience :: Science/Research
Classifier: License :: OSI Approved :: MIT License
Classifier: Programming Language :: Python :: 2
Classifier: Programming Language :: Python :: 3
Classifier: Topic :: Scientific/Engineering
Classifier: Topic :: Scientific/Engineering :: Artificial Intelligence
Classifier: Topic :: Software Development
Classifier: Topic :: Software Development :: Libraries
Classifier: Topic :: Software Development :: Libraries :: Python Modules
Provides-Extra: tf_gpu
Provides-Extra: tf_cpu
Provides-Extra: tf_cpu
Requires-Dist: tensorflow (>=2.0.0-alpha0); extra == 'tf_cpu'
Provides-Extra: tf_gpu
Requires-Dist: tensorflow-gpu (>=2.0.0-alpha0); extra == 'tf_gpu'
